odoo10_addon_contract_payment_auto-10.0.1.0.1-py2.7-nspkg.pth
odoo/addons/contract_payment_auto/README.rst
odoo/addons/contract_payment_auto/__init__.py
odoo/addons/contract_payment_auto/__manifest__.py
odoo/addons/contract_payment_auto/data/ir_cron_data.xml
odoo/addons/contract_payment_auto/data/mail_template_data.xml
odoo/addons/contract_payment_auto/i18n/ca.po
odoo/addons/contract_payment_auto/i18n/de.po
odoo/addons/contract_payment_auto/i18n/el_GR.po
odoo/addons/contract_payment_auto/i18n/es.po
odoo/addons/contract_payment_auto/i18n/es_MX.po
odoo/addons/contract_payment_auto/i18n/fi.po
odoo/addons/contract_payment_auto/i18n/fr.po
odoo/addons/contract_payment_auto/i18n/gl.po
odoo/addons/contract_payment_auto/i18n/hi_IN.po
odoo/addons/contract_payment_auto/i18n/hr.po
odoo/addons/contract_payment_auto/i18n/hr_HR.po
odoo/addons/contract_payment_auto/i18n/hu.po
odoo/addons/contract_payment_auto/i18n/it.po
odoo/addons/contract_payment_auto/i18n/nl.po
odoo/addons/contract_payment_auto/i18n/nl_NL.po
odoo/addons/contract_payment_auto/i18n/pt.po
odoo/addons/contract_payment_auto/i18n/pt_BR.po
odoo/addons/contract_payment_auto/i18n/pt_PT.po
odoo/addons/contract_payment_auto/i18n/ro.po
odoo/addons/contract_payment_auto/i18n/ru.po
odoo/addons/contract_payment_auto/i18n/sk_SK.po
odoo/addons/contract_payment_auto/i18n/sl.po
odoo/addons/contract_payment_auto/i18n/tr.po
odoo/addons/contract_payment_auto/i18n/tr_TR.po
odoo/addons/contract_payment_auto/i18n/zh_CN.po
odoo/addons/contract_payment_auto/models/__init__.py
odoo/addons/contract_payment_auto/models/account_analytic_account.py
odoo/addons/contract_payment_auto/models/account_analytic_contract.py
odoo/addons/contract_payment_auto/models/account_invoice.py
odoo/addons/contract_payment_auto/models/res_partner.py
odoo/addons/contract_payment_auto/tests/__init__.py
odoo/addons/contract_payment_auto/tests/test_account_analytic_account.py
odoo10_addon_contract_payment_auto-10.0.1.0.1.dist-info/DESCRIPTION.rst
odoo10_addon_contract_payment_auto-10.0.1.0.1.dist-info/METADATA
odoo10_addon_contract_payment_auto-10.0.1.0.1.dist-info/RECORD
odoo10_addon_contract_payment_auto-10.0.1.0.1.dist-info/WHEEL
odoo10_addon_contract_payment_auto-10.0.1.0.1.dist-info/metadata.json
odoo10_addon_contract_payment_auto-10.0.1.0.1.dist-info/namespace_packages.txt
odoo10_addon_contract_payment_auto-10.0.1.0.1.dist-info/top_level.txt
